README.rst
setup.py
pyoptionchain/__init__.py
pyoptionchain/commands.py
pyoptionchain/google_api.py
pyoptionchain/pandas_utility.py
pyoptionchain/tk_gui.py
pyoptionchain.egg-info/PKG-INFO
pyoptionchain.egg-info/SOURCES.txt
pyoptionchain.egg-info/dependency_links.txt
pyoptionchain.egg-info/entry_points.txt
pyoptionchain.egg-info/requires.txt
pyoptionchain.egg-info/top_level.txt